{
  "resourceType": "StructureDefinition",
  "id": "ISiKOrganisation",
  "url": "https://gematik.de/fhir/isik/v3/Basismodul/StructureDefinition/ISiKOrganisation",
  "version": "4.0.0-rc",
  "name": "ISiKOrganisation",
  "status": "draft",
  "experimental": false,
  "date": "2024-01-16",
  "publisher": "gematik GmbH",
  "description": "Dieses Profil beschreibt die Nutzung von Organisationseinheiten innerhalb eines Krankenhauses oder eines Krankenhauses als ganzem in ISiK-Szenarien.",
  "fhirVersion": "4.0.1",
  "mapping": [
    {
      "identity": "v2",
      "uri": "http://hl7.org/v2",
      "name": "HL7 v2 Mapping"
    },
    {
      "identity": "rim",
      "uri": "http://hl7.org/v3",
      "name": "RIM Mapping"
    },
    {
      "identity": "servd",
      "uri": "http://www.omg.org/spec/ServD/1.0/",
      "name": "ServD"
    },
    {
      "identity": "w5",
      "uri": "http://hl7.org/fhir/fivews",
      "name": "FiveWs Pattern Mapping"
    }
  ],
  "kind": "resource",
  "abstract": false,
  "type": "Organization",
  "baseDefinition": "http://hl7.org/fhir/StructureDefinition/Organization",
  "derivation": "constraint",
  "differential": {
    "element": [
      {
        "id": "Organization.id",
        "path": "Organization.id",
        "mustSupport": true
      },
      {
        "id": "Organization.identifier",
        "path": "Organization.identifier",
        "slicing": {
          "discriminator": [
            {
              "type": "pattern",
              "path": "$this"
            }
          ],
          "rules": "open"
        },
        "min": 1,
        "mustSupport": true
      },
      {
        "id": "Organization.identifier:IKNR",
        "path": "Organization.identifier",
        "sliceName": "IKNR",
        "min": 0,
        "max": "1",
        "type": [
          {
            "code": "Identifier",
            "profile": [
              "http://fhir.de/StructureDefinition/identifier-iknr"
            ]
          }
        ],
        "mustSupport": true
      },
      {
        "id": "Organization.identifier:IKNR.type",
        "path": "Organization.identifier.type",
        "comment": "Motivation: Entsprechend der Vorgabe der KBV Organisation 1.5.0. (https://fhir.kbv.de/StructureDefinition/KBV_PR_Base_Organization), muss ein System ein Institutionskennzeichen (IKNR) verarbeiten können, sofern diese Information bereitgestellt wird. "
      },
      {
        "id": "Organization.identifier:BSNR",
        "path": "Organization.identifier",
        "sliceName": "BSNR",
        "min": 0,
        "max": "1",
        "type": [
          {
            "code": "Identifier",
            "profile": [
              "http://fhir.de/StructureDefinition/identifier-bsnr"
            ]
          }
        ],
        "mustSupport": true
      },
      {
        "id": "Organization.identifier:BSNR.type",
        "path": "Organization.identifier.type",
        "comment": "Motivation: Entsprechend der Bedarfsmeldung im Rahmen der Stakeholderbefragung zu einem Profil Organisation in der Arbeitsgruppe zum ISIK Basismodul Stufe 4 und der Vorgabe der KBV Organisation 1.5.0. (https://fhir.kbv.de/StructureDefinition/KBV_PR_Base_Organization), muss ein System eine Betriebsstättennummer (BSNR) verarbeiten können, sofern diese Information bereitgestellt wird. "
      },
      {
        "id": "Organization.active",
        "path": "Organization.active",
        "comment": "Motivation: Ein System oder eine Person muss prüfen können, ob eine Organisation aktiv ist oder nicht, sofern diese Information bereitgestellt wird.",
        "mustSupport": true
      },
      {
        "id": "Organization.type",
        "path": "Organization.type",
        "comment": "Motivation: Ein System oder eine Person muss den Typ einer Organisation abrufen können, sofern diese Information bereitgestellt wird. \r\n  Die Festlegung einer endlichen Menge von Organisations-Formen in verbindlicher weise, ist zum Zeitpunkt der Festlegung nicht möglich.",
        "mustSupport": true
      },
      {
        "id": "Organization.name",
        "path": "Organization.name",
        "comment": "Motivation: Einer Organisation oder Organisationseinheit muss ein Name zugewiesen werden.",
        "min": 1,
        "mustSupport": true
      },
      {
        "id": "Organization.alias",
        "path": "Organization.alias",
        "comment": "Motivation: Ein System oder eine Person muss den Alias einer Organisation abrufen können, sofern diese Information bereitgestellt wird.",
        "mustSupport": true
      },
      {
        "id": "Organization.telecom",
        "path": "Organization.telecom",
        "comment": "Motivation: Ein System oder eine Person muss Kontaktinformation einer Organisation abrufen können, sofern diese Information bereitgestellt wird.",
        "mustSupport": true
      },
      {
        "id": "Organization.address",
        "path": "Organization.address",
        "comment": "Motivation: Ein System oder eine Person muss Adressinformationen einer Organisation abrufen können, sofern diese Information bereitgestellt wird.",
        "mustSupport": true
      },
      {
        "id": "Organization.partOf",
        "path": "Organization.partOf",
        "comment": "Motivation: System oder eine Person muss die Hierarchie einer Organisationseinheit innherhalb einer Organisation abrufen können, sofern diese Information bereitgestellt wird.",
        "mustSupport": true
      },
      {
        "id": "Organization.contact",
        "path": "Organization.contact",
        "comment": "Motivation: Ein System oder eine Person muss Kontaktinformation einer Organisation abrufen können, sofern diese Information bereitgestellt wird.",
        "mustSupport": true
      },
      {
        "id": "Organization.endpoint",
        "path": "Organization.endpoint",
        "comment": "Motivation: Ein System oder eine Person muss den technischen Endpunt einer Organisation abrufen können, sofern diese Information bereitgestellt wird.",
        "mustSupport": true
      }
    ]
  }
}
