{
  "resourceType": "ValueSet",
  "status": "draft",
  "name": "ISiKDiagnoseTyp",
  "id": "ISiKDiagnoseTyp",
  "version": "2.0.0",
  "url": "https://gematik.de/fhir/ISiK/v2/ValueSet/ISiKDiagnoseTyp",
  "experimental": false,
  "publisher": "gematik GmbH",
  "date": "2021-11-12",
  "compose": {
    "include": [
      {
        "system": "https://gematik.de/fhir/ISiK/v2/CodeSystem/ISiKKontaktDiagnose",
        "concept": [
          {
            "code": "referral-diagnosis",
            "display": "Überweisungsdiagnose"
          },
          {
            "code": "treatment-diagnosis",
            "display": "Behandlungsdiagnose"
          }
        ]
      }
    ]
  }
}
